Xml/__init__.py
Xml/dom/Documents.py
Xml/dom/__init__.py
clndr/__init__.py
clndr/calendar_event.py
clndr/time_line.py
clndr/management/__init__.py
clndr/management/commands/__init__.py
clndr/management/commands/build_test.py
clndr/management/commands/build_time_line.py
clndr/migrations/0001_initial.py
clndr/migrations/0002_day_shifts.py
clndr/migrations/0003_holidays.py
clndr/migrations/0004_calendar_shits_days.py
clndr/migrations/0005_auto_20190821_0056.py
clndr/migrations/0006_auto_20190821_0100.py
clndr/migrations/0007_shift_day.py
clndr/migrations/0008_auto_20190821_0109.py
clndr/migrations/0009_auto_20190821_0110.py
clndr/migrations/0010_calendars_parent.py
clndr/migrations/0011_auto_20190821_0820.py
clndr/migrations/0012_holidays_props.py
clndr/migrations/0013_auto_20190821_1241.py
clndr/migrations/0014_holidays_view.py
clndr/migrations/0015_day_types.py
clndr/migrations/0016_remove_holidays_props.py
clndr/migrations/0017_holidays_day_type.py
clndr/migrations/0018_auto_20190821_1721.py
clndr/migrations/0019_delete_holidays_view.py
clndr/migrations/0020_remove_shift_day_props.py
clndr/migrations/0021_shift_day_daytype.py
clndr/migrations/0022_auto_20190821_2016.py
clndr/migrations/0023_auto_20190822_1052.py
clndr/migrations/0024_auto_20190822_1100.py
clndr/migrations/0025_shift_day_dinnertime.py
clndr/migrations/0026_auto_20190822_2217.py
clndr/migrations/0027_auto_20190822_2222.py
clndr/migrations/0028_auto_20190822_2222.py
clndr/migrations/0029_auto_20190822_2234.py
clndr/migrations/0030_auto_20190822_2236.py
clndr/migrations/0031_auto_20190822_2239.py
clndr/migrations/0032_auto_20190822_2239.py
clndr/migrations/0033_auto_20190822_2250.py
clndr/migrations/0034_auto_20190823_0350.py
clndr/migrations/0035_delete_calendar_shifts_days.py
clndr/migrations/0036_auto_20190823_0357.py
clndr/migrations/0037_auto_20190823_0929.py
clndr/migrations/0038_auto_20190823_0948.py
clndr/migrations/0039_remove_shift_day_calendar.py
clndr/migrations/0040_auto_20190823_1503.py
isc_py_common-0.1.27.dist-info/LICENSE.txt
isc_py_common-0.1.27.dist-info/METADATA
isc_py_common-0.1.27.dist-info/WHEEL
isc_py_common-0.1.27.dist-info/entry_points.txt
isc_py_common-0.1.27.dist-info/top_level.txt
isc_py_common-0.1.27.dist-info/RECORD
