Metadata-Version: 2.1
Name: isc-py-common
Version: 0.1.27
Summary: ISC Python common project
Home-page: UNKNOWN
Author: Andrey Yudin
Author-email: uag@ivc-inform.ru
License: UNKNOWN
Project-URL: Source, https://github.com/ivc-inform/isc-py-common.git
Keywords: isc setuptools development common
Platform: UNKNOWN
Classifier: Development Status :: 3 - Alpha
Classifier: Intended Audience :: Developers
Classifier: Topic :: Software Development :: Build Tools
Classifier: License :: OSI Approved :: MIT License
Classifier: Programming Language :: Python :: 3.8
Classifier: Programming Language :: Python :: 3.7
Classifier: Programming Language :: Python :: 3.6
Requires-Python: >=3.8
